tensorimage/__init__.py
tensorimage/base/__init__.py
tensorimage/base/display_architecture.py
tensorimage/base/l2_regularization.py
tensorimage/base/metadata_reader.py
tensorimage/base/model.py
tensorimage/base/ops.py
tensorimage/base/weights_initializer.py
tensorimage/base/models/__init__.py
tensorimage/base/models/alexnet.py
tensorimage/base/models/rosnet.py
tensorimage/base/models/map/__init__.py
tensorimage/base/models/map/model.py
tensorimage/classify/__init__.py
tensorimage/classify/classifier.py
tensorimage/config/__init__.py
tensorimage/config/config.json
tensorimage/config/info.py
tensorimage/config/manager.py
tensorimage/data_augmentation/__init__.py
tensorimage/data_augmentation/_base.py
tensorimage/data_augmentation/blur.py
tensorimage/data_augmentation/color.py
tensorimage/data_augmentation/flip.py
tensorimage/data_augmentation/maths.py
tensorimage/data_augmentation/property.py
tensorimage/data_augmentation/transform.py
tensorimage/dataset/__init__.py
tensorimage/dataset/label_writer.py
tensorimage/dataset/path_writer.py
tensorimage/file/__init__.py
tensorimage/file/reader.py
tensorimage/file/writer.py
tensorimage/image/__init__.py
tensorimage/image/display.py
tensorimage/image/loader.py
tensorimage/image/writer.py
tensorimage/train/__init__.py
tensorimage/train/cluster_trainer.py
tensorimage/train/trainer.py
tensorimage/util/__init__.py
tensorimage/util/log.py
tensorimage/util/system/__init__.py
tensorimage/util/system/make_file.py
tensorimage/util/system/make_workspace.py
tensorimage/util/system/mkdir.py
tensorimage/util/system/os.py
TensorImage-2.1.0.dist-info/LICENSE.md
TensorImage-2.1.0.dist-info/METADATA
TensorImage-2.1.0.dist-info/WHEEL
TensorImage-2.1.0.dist-info/top_level.txt
TensorImage-2.1.0.dist-info/RECORD
