Metadata-Version: 2.1
Name: TensorImage
Version: 2.1.0
Summary: Image classification library for easily and quickly deploying models and training classifiers
Home-page: https://github.com/TensorImage/TensorImage
Author: TensorImage
Author-email: tensor.image2@gmail.com
License: UNKNOWN
Platform: UNKNOWN
Classifier: Programming Language :: Python :: 3
Classifier: Operating System :: POSIX
Requires-Dist: tensorflow (>=1.9.0)
Requires-Dist: tensorboard
Requires-Dist: Pillow (>=5.1.0)
Requires-Dist: scikit-learn (>=0.19.1)
Requires-Dist: numpy (>=1.14.5)
Requires-Dist: pandas (>=0.22.0)
Requires-Dist: opencv-python (>=3.4.0.12)
Requires-Dist: progress
Requires-Dist: scipy
